DataCollectionMain.py
FactorTestBox.py
FactorTestMain.py
FactorTestPara.py
FactorTestPerformance.py
UpdateRawData.py
FactorTest-1.0.8.dist-info/METADATA
FactorTest-1.0.8.dist-info/WHEEL
FactorTest-1.0.8.dist-info/top_level.txt
FactorTest-1.0.8.dist-info/RECORD
