Metadata-Version: 2.1
Name: FactorTest
Version: 1.0.8
Summary: zxy 框架
Home-page: https://github.com/jltxzxy/FactorTest.git
Author: zhangxaingyu
Author-email: 376184494@qq.com
License: MIT
Platform: UNKNOWN
